MANIFEST.in
README.md
requirements-dev.txt
requirements.txt
setup.py
FACe_lib.egg-info/PKG-INFO
FACe_lib.egg-info/SOURCES.txt
FACe_lib.egg-info/dependency_links.txt
FACe_lib.egg-info/requires.txt
FACe_lib.egg-info/top_level.txt
face/__init__.py
face/face.py
face/codes/__init__.py
face/codes/result.py
face/codes/status.py
face/models/__init__.py
face/models/administrations.py
face/models/invoice.py
face/models/response.py
face/models/status.py
face/services/__init__.py
face/services/administration.py
face/services/invoice.py
face/services/nif.py
face/services/service.py