Metadata-Version: 1.1
Name: FACe-lib
Version: 0.2.10
Summary: FACe interface to simplify the interaction with their webservices
Home-page: http://www.gisce.net
Author: GISCE-TI, S.L.
Author-email: devel@gisce.net
License: GNU GPLv3
Platform: UNKNOWN
Classifier: Programming Language :: Python
Classifier: Programming Language :: Python :: 2.7
Provides: FACe_lib
